Metadata-Version: 1.1
Name: django-easy-rest
Version: 3.1
Summary: A simple Django app to create rest applications
Home-page: https://github.com/jonatanSh/django-easy-rest/
Author: Jonathan Shimon
Author-email: jonatanshimon@gmail.com
License: MIT License
Platform: UNKNOWN
Classifier: Environment :: Web Environment
Classifier: Framework :: Django
Classifier: Intended Audience :: Developers
Classifier: License :: OSI Approved :: MIT License
Classifier: Operating System :: OS Independent
Classifier: Programming Language :: Python :: 3
Classifier: Programming Language :: Python :: 3.2
Classifier: Programming Language :: Python :: 3.3
Classifier: Programming Language :: Python :: 3.4
Classifier: Programming Language :: Python :: 3.4
Classifier: Programming Language :: Python :: 3.5
